gtdb_tree-0.1.9.dist-info/METADATA
gtdb_tree-0.1.9.dist-info/WHEEL
gtdb_tree-0.1.9.dist-info/licenses/license
gtdb_tree/__init__.py
gtdb_tree/gtdb_tree.cp38-win32.pyd
gtdb_tree-0.1.9.dist-info/RECORD
