Metadata-Version: 2.3
Name: gtdb_tree
Version: 0.1.9
Classifier: License :: OSI Approved :: MIT License
Classifier: Programming Language :: Python
Classifier: Programming Language :: Python :: 3
Classifier: Programming Language :: Rust
Requires-Dist: setuptools-rust >=1.5.2
License-File: license
Summary: A Python package for parsing GTDB trees using Rust
Keywords: gtdb,tree,parser,rust
Home-Page: https://github.com/eric9n/gtdb_tree
Author: dagou <eric9n@gmail.com>
Author-email: dagou <eric9n@gmail.com>
License: MIT
Requires-Python: >=3.8
Project-URL: Homepage, https://github.com/eric9n/gtdb_tree
